{"data":{"Level13":[{"date":"2004/8/8","name":"Mr. Default","score":4000},{"date":"2004/8/8","name":"Mr. Default","score":3600},{"date":"2004/8/8","name":"Mr. Default","score":3200},{"date":"2004/8/8","name":"Mr. Default","score":2800},{"date":"2004/8/8","name":"Mr. Default","score":2400},{"date":"2004/8/8","name":"Mr. Default","score":2000},{"date":"2004/8/8","name":"Mr. Default","score":1600},{"date":"2004/8/8","name":"Mr. Default","score":1200},{"date":"2004/8/8","name":"Mr. Default","score":800},{"date":"2004/8/8","name":"Mr. Default","score":400}],"Level06":[{"date":"2004/8/8","name":"Mr. Default","score":4000},{"date":"2004/8/8","name":"Mr. Default","score":3600},{"date":"2004/8/8","name":"Mr. Default","score":3200},{"date":"2004/8/8","name":"Mr. Default","score":2800},{"date":"2004/8/8","name":"Mr. Default","score":2400},{"date":"2004/8/8","name":"Mr. Default","score":2000},{"date":"2004/8/8","name":"Mr. Default","score":1600},{"date":"2004/8/8","name":"Mr. Default","score":1200},{"date":"2004/8/8","name":"Mr. Default","score":800},{"date":"2004/8/8","name":"Mr. Default","score":400}],"Level04":[{"date":"2004/8/8","name":"Mr. Default","score":4000},{"date":"2004/8/8","name":"Mr. Default","score":3600},{"date":"2004/8/8","name":"Mr. Default","score":3200},{"date":"2004/8/8","name":"Mr. Default","score":2800},{"date":"2004/8/8","name":"Mr. Default","score":2400},{"date":"2004/8/8","name":"Mr. Default","score":2000},{"date":"2004/8/8","name":"Mr. Default","score":1600},{"date":"2004/8/8","name":"Mr. Default","score":1200},{"date":"2004/8/8","name":"Mr. Default","score":800},{"date":"2004/8/8","name":"Mr. Default","score":400}],"Level08":[{"date":"2004/8/8","name":"Mr. Default","score":4000},{"date":"2004/8/8","name":"Mr. Default","score":3600},{"date":"2004/8/8","name":"Mr. Default","score":3200},{"date":"2004/8/8","name":"Mr. Default","score":2800},{"date":"2004/8/8","name":"Mr. Default","score":2400},{"date":"2004/8/8","name":"Mr. Default","score":2000},{"date":"2004/8/8","name":"Mr. Default","score":1600},{"date":"2004/8/8","name":"Mr. Default","score":1200},{"date":"2004/8/8","name":"Mr. Default","score":800},{"date":"2004/8/8","name":"Mr. Default","score":400}],"Level12":[{"date":"2004/8/8","name":"Mr. Default","score":7000},{"date":"2004/8/8","name":"Mr. Default","score":6600},{"date":"2004/8/8","name":"Mr. Default","score":6200},{"date":"2004/8/8","name":"Mr. Default","score":5800},{"date":"2004/8/8","name":"Mr. Default","score":5400},{"date":"2004/8/8","name":"Mr. Default","score":5000},{"date":"2004/8/8","name":"Mr. Default","score":4600},{"date":"2004/8/8","name":"Mr. Default","score":4200},{"date":"2004/8/8","name":"Mr. Default","score":3800},{"date":"2004/8/8","name":"Mr. Default","score":3600}],"Level03":[{"date":"2004/8/8","name":"Mr. Default","score":4000},{"date":"2004/8/8","name":"Mr. Default","score":3600},{"date":"2004/8/8","name":"Mr. Default","score":3200},{"date":"2004/8/8","name":"Mr. Default","score":2800},{"date":"2004/8/8","name":"Mr. Default","score":2400},{"date":"2004/8/8","name":"Mr. Default","score":2000},{"date":"2004/8/8","name":"Mr. Default","score":1600},{"date":"2004/8/8","name":"Mr. Default","score":1200},{"date":"2004/8/8","name":"Mr. Default","score":800},{"date":"2004/8/8","name":"Mr. Default","score":400}],"Level07":[{"date":"2004/8/8","name":"Mr. Default","score":4000},{"date":"2004/8/8","name":"Mr. Default","score":3600},{"date":"2004/8/8","name":"Mr. Default","score":3200},{"date":"2004/8/8","name":"Mr. Default","score":2800},{"date":"2004/8/8","name":"Mr. Default","score":2400},{"date":"2004/8/8","name":"Mr. Default","score":2000},{"date":"2004/8/8","name":"Mr. Default","score":1600},{"date":"2004/8/8","name":"Mr. Default","score":1200},{"date":"2004/8/8","name":"Mr. Default","score":800},{"date":"2004/8/8","name":"Mr. Default","score":400}],"Level02":[{"date":"2004/8/8","name":"Mr. Default","score":4000},{"date":"2004/8/8","name":"Mr. Default","score":3600},{"date":"2004/8/8","name":"Mr. Default","score":3200},{"date":"2004/8/8","name":"Mr. Default","score":2800},{"date":"2004/8/8","name":"Mr. Default","score":2400},{"date":"2004/8/8","name":"Mr. Default","score":2000},{"date":"2004/8/8","name":"Mr. Default","score":1600},{"date":"2004/8/8","name":"Mr. Default","score":1200},{"date":"2004/8/8","name":"Mr. Default","score":800},{"date":"2004/8/8","name":"Mr. Default","score":400}],"Level01":[{"date":"2004/8/8","name":"Mr. Default","score":4000},{"date":"2004/8/8","name":"Mr. Default","score":3600},{"date":"2004/8/8","name":"Mr. Default","score":3200},{"date":"2004/8/8","name":"Mr. Default","score":2800},{"date":"2004/8/8","name":"Mr. Default","score":2400},{"date":"2004/8/8","name":"Mr. Default","score":2000},{"date":"2004/8/8","name":"Mr. Default","score":1600},{"date":"2004/8/8","name":"Mr. Default","score":1200},{"date":"2004/8/8","name":"Mr. Default","score":800},{"date":"2004/8/8","name":"Mr. Default","score":400}],"Level09":[{"date":"2004/8/8","name":"Mr. Default","score":4000},{"date":"2004/8/8","name":"Mr. Default","score":3600},{"date":"2004/8/8","name":"Mr. Default","score":3200},{"date":"2004/8/8","name":"Mr. Default","score":2800},{"date":"2004/8/8","name":"Mr. Default","score":2400},{"date":"2004/8/8","name":"Mr. Default","score":2000},{"date":"2004/8/8","name":"Mr. Default","score":1600},{"date":"2004/8/8","name":"Mr. Default","score":1200},{"date":"2004/8/8","name":"Mr. Default","score":800},{"date":"2004/8/8","name":"Mr. Default","score":400}],"Level10":[{"date":"2004/8/8","name":"Mr. Default","score":4000},{"date":"2004/8/8","name":"Mr. Default","score":3600},{"date":"2004/8/8","name":"Mr. Default","score":3200},{"date":"2004/8/8","name":"Mr. Default","score":2800},{"date":"2004/8/8","name":"Mr. Default","score":2400},{"date":"2004/8/8","name":"Mr. Default","score":2000},{"date":"2004/8/8","name":"Mr. Default","score":1600},{"date":"2004/8/8","name":"Mr. Default","score":1200},{"date":"2004/8/8","name":"Mr. Default","score":800},{"date":"2004/8/8","name":"Mr. Default","score":400}],"Level11":[{"date":"2004/8/8","name":"Mr. Default","score":4000},{"date":"2004/8/8","name":"Mr. Default","score":3600},{"date":"2004/8/8","name":"Mr. Default","score":3200},{"date":"2004/8/8","name":"Mr. Default","score":2800},{"date":"2004/8/8","name":"Mr. Default","score":2400},{"date":"2004/8/8","name":"Mr. Default","score":2000},{"date":"2004/8/8","name":"Mr. Default","score":1600},{"date":"2004/8/8","name":"Mr. Default","score":1200},{"date":"2004/8/8","name":"Mr. Default","score":800},{"date":"2004/8/8","name":"Mr. Default","score":400}],"Level05":[{"date":"2004/8/8","name":"Mr. Default","score":4000},{"date":"2004/8/8","name":"Mr. Default","score":3600},{"date":"2004/8/8","name":"Mr. Default","score":3200},{"date":"2004/8/8","name":"Mr. Default","score":2800},{"date":"2004/8/8","name":"Mr. Default","score":2400},{"date":"2004/8/8","name":"Mr. Default","score":2000},{"date":"2004/8/8","name":"Mr. Default","score":1600},{"date":"2004/8/8","name":"Mr. Default","score":1200},{"date":"2004/8/8","name":"Mr. Default","score":800},{"date":"2004/8/8","name":"Mr. Default","score":400}]},"names":["Level01","Level02","Level03","Level04","Level05","Level06","Level07","Level08","Level09","Level10","Level11","Level12"]}